{
    "description": "PxMatrix LED MATRIX library for ESP8266, ESP32 and ATMEL", 
    "repository": {
        "url": "https://github.com/2dom/PxMatrix", 
        "type": "git"
    }, 
    "platforms": [
        "atmelavr", 
        "atmelsam", 
        "espressif32", 
        "espressif8266", 
        "gd32v", 
        "infineonxmc", 
        "intel_arc32", 
        "kendryte210", 
        "microchippic32", 
        "nordicnrf51", 
        "nordicnrf52", 
        "ststm32", 
        "ststm8", 
        "teensy", 
        "timsp430"
    ], 
    "export": {
        "exclude": [
            "extras", 
            "docs", 
            "tests", 
            "test", 
            "*.doxyfile", 
            "*.pdf"
        ], 
        "include": null
    }, 
    "authors": [
        {
            "maintainer": true, 
            "name": "Dominic Buchstaller", 
            "url": null, 
            "email": "dbuchstaller@web.de"
        }
    ], 
    "keywords": [
        "display"
    ], 
    "id": 5437, 
    "name": "PxMatrix LED MATRIX library", 
    "frameworks": [
        "arduino"
    ], 
    "version": "1.7.0", 
    "homepage": null
}